README
setup.py
vhm_check.py
vhmcli.py
vhm_client.egg-info/PKG-INFO
vhm_client.egg-info/SOURCES.txt
vhm_client.egg-info/dependency_links.txt
vhm_client.egg-info/requires.txt
vhm_client.egg-info/top_level.txt
vhmlib/__init__.py
vhmlib/config.py
vhmlib/manager.py
vhmlib/repository.py
vhmlib/system.py
vhmlib/user.py
vhmlib/utils.py
vhmlib/vhmcli.py
vhmlib/vhmserver.py