Metadata-Version: 1.1
Name: vhm-client
Version: 0.3.2
Summary: Client for manage system and project VHM.
Home-page: https://github.com/Pajinek/vhm
Author: Pavel Studenik
Author-email: studenik@varhoo.cz
License: GPL
Keywords: Client for varhoo manage system
Platform: UNKNOWN
Classifier: Development Status :: 3 - Alpha
Classifier: Topic :: Utilities
Classifier: License :: OSI Approved :: GNU General Public License (GPL)
Classifier: Programming Language :: Python :: 2.7
